polaris/__init__.py
polaris/_artifact.py
polaris/_version.py
polaris/cli.py
polaris/benchmark/__init__.py
polaris/benchmark/_base.py
polaris/benchmark/_benchmark_v2.py
polaris/benchmark/_definitions.py
polaris/benchmark/_split.py
polaris/benchmark/_split_v2.py
polaris/benchmark/_task.py
polaris/competition/__init__.py
polaris/dataset/__init__.py
polaris/dataset/_adapters.py
polaris/dataset/_base.py
polaris/dataset/_column.py
polaris/dataset/_dataset.py
polaris/dataset/_dataset_v2.py
polaris/dataset/_factory.py
polaris/dataset/_subset.py
polaris/dataset/converters/__init__.py
polaris/dataset/converters/_base.py
polaris/dataset/converters/_pdb.py
polaris/dataset/converters/_sdf.py
polaris/dataset/converters/_zarr.py
polaris/dataset/zarr/__init__.py
polaris/dataset/zarr/_checksum.py
polaris/dataset/zarr/_manifest.py
polaris/dataset/zarr/_memmap.py
polaris/dataset/zarr/_utils.py
polaris/dataset/zarr/codecs.py
polaris/evaluate/__init__.py
polaris/evaluate/_metadata.py
polaris/evaluate/_metric.py
polaris/evaluate/_predictions.py
polaris/evaluate/_results.py
polaris/evaluate/utils.py
polaris/evaluate/metrics/__init__.py
polaris/evaluate/metrics/docking_metrics.py
polaris/evaluate/metrics/generic_metrics.py
polaris/experimental/__init__.py
polaris/hub/__init__.py
polaris/hub/client.py
polaris/hub/external_client.py
polaris/hub/oauth.py
polaris/hub/settings.py
polaris/hub/storage.py
polaris/loader/__init__.py
polaris/loader/load.py
polaris/mixins/__init__.py
polaris/mixins/_checksum.py
polaris/mixins/_format_text.py
polaris/model/__init__.py
polaris/utils/__init__.py
polaris/utils/constants.py
polaris/utils/context.py
polaris/utils/dict2html.py
polaris/utils/errors.py
polaris/utils/misc.py
polaris/utils/types.py
polaris_lib-0.13.0.dist-info/licenses/LICENSE
polaris_lib-0.13.0.dist-info/licenses/NOTICE
polaris_lib-0.13.0.dist-info/METADATA
polaris_lib-0.13.0.dist-info/WHEEL
polaris_lib-0.13.0.dist-info/entry_points.txt
polaris_lib-0.13.0.dist-info/top_level.txt
polaris_lib-0.13.0.dist-info/RECORD
