Metadata-Version: 2.4
Name: polaris-lib
Version: 0.13.0
Summary: Client for the Polaris Hub.
Author-email: Cas Wognum <cas@valencelabs.com>, Lu Zhu <lu@valencelabs.com>, Andrew Quirke <andrew@valencelabs.com>, Julien St-Laurent <julien.stl@valencelabs.com>
Project-URL: Website, https://polarishub.io/
Project-URL: Source Code, https://github.com/polaris-hub/polaris
Project-URL: Bug Tracker, https://github.com/polaris-hub/polaris/issues
Project-URL: Documentation, https://polaris-hub.github.io/polaris/
Classifier: Development Status :: 5 - Production/Stable
Classifier: Intended Audience :: Developers
Classifier: Intended Audience :: Healthcare Industry
Classifier: Intended Audience :: Science/Research
Classifier: Topic :: Scientific/Engineering :: Artificial Intelligence
Classifier: Topic :: Scientific/Engineering :: Bio-Informatics
Classifier: Topic :: Scientific/Engineering :: Information Analysis
Classifier: Topic :: Scientific/Engineering :: Medical Science Apps.
Classifier: Natural Language :: English
Classifier: Operating System :: OS Independent
Classifier: Programming Language :: Python
Classifier: Programming Language :: Python :: 3
Classifier: Programming Language :: Python :: 3.10
Classifier: Programming Language :: Python :: 3.11
Classifier: Programming Language :: Python :: 3.12
Requires-Python: <3.13,>=3.10
License-File: LICENSE
License-File: NOTICE
Requires-Dist: authlib
Requires-Dist: boto3<1.36.0
Requires-Dist: datamol>=0.12.1
Requires-Dist: fastpdb
Requires-Dist: fsspec[http]
Requires-Dist: httpx
Requires-Dist: numcodecs[msgpack]<0.16.0,>=0.13.1
Requires-Dist: numpy<3
Requires-Dist: pandas
Requires-Dist: pyarrow<18
Requires-Dist: pydantic>=2
Requires-Dist: pydantic-settings>=2
Requires-Dist: pyroaring
Requires-Dist: pyyaml
Requires-Dist: rich>=13.9.4
Requires-Dist: scikit-learn
Requires-Dist: scipy
Requires-Dist: seaborn
Requires-Dist: typer
Requires-Dist: typing-extensions>=4.12.0
Requires-Dist: zarr<3,>=2
Provides-Extra: dev
Requires-Dist: ipywidgets; extra == "dev"
Requires-Dist: jupyterlab; extra == "dev"
Requires-Dist: moto[s3]>=5.0.14; extra == "dev"
Requires-Dist: pytest>=7; extra == "dev"
Requires-Dist: pytest-xdist; extra == "dev"
Requires-Dist: pytest-cov; extra == "dev"
Requires-Dist: ruff; extra == "dev"
Provides-Extra: doc
Requires-Dist: mkdocs; extra == "doc"
Requires-Dist: mkdocs-material>=9.4.7; extra == "doc"
Requires-Dist: mkdocstrings; extra == "doc"
Requires-Dist: mkdocstrings-python; extra == "doc"
Requires-Dist: mkdocs-jupyter; extra == "doc"
Requires-Dist: markdown-include; extra == "doc"
Requires-Dist: mdx_truly_sane_lists; extra == "doc"
Requires-Dist: mike>=1.0.0; extra == "doc"
Requires-Dist: nbconvert; extra == "doc"
Provides-Extra: codecs
Requires-Dist: imagecodecs; extra == "codecs"
Dynamic: license-file
